Metadata-Version: 1.0
Name: shivam-PD
Version: 1.0
Summary: This python package is created to help user to perform complex mathematical operations in Probability Distribution.
Home-page: UNKNOWN
Author: Shivam Chaubey
Author-email: shivamchaubey83@gmail.com
License: UNKNOWN
Platform: UNKNOWN
